pydantic_settings_doppler/__init__.py
pydantic_settings_doppler/logger.py
pydantic_settings_doppler/source.py
pydantic_settings_doppler-0.1.2.dist-info/LICENSE
pydantic_settings_doppler-0.1.2.dist-info/METADATA
pydantic_settings_doppler-0.1.2.dist-info/WHEEL
pydantic_settings_doppler-0.1.2.dist-info/RECORD
