Metadata-Version: 2.3
Name: pydantic-settings-doppler
Version: 0.1.2
Summary: Settings management for Pydantic models using Doppler
License: MIT
Keywords: pydantic,settings,doppler,configuration,environment variables
Author: Algirdas Jauniskis
Author-email: jauniskis.a@gmail.com
Requires-Python: >=3.9
Classifier: Development Status :: 4 - Beta
Classifier: Programming Language :: Python
Classifier: Programming Language :: Python :: 3
Classifier: Programming Language :: Python :: 3 :: Only
Classifier: Programming Language :: Python :: 3.9
Classifier: Programming Language :: Python :: 3.10
Classifier: Programming Language :: Python :: 3.11
Classifier: Programming Language :: Python :: 3.12
Classifier: Programming Language :: Python :: 3.13
Classifier: Programming Language :: Python :: Implementation :: CPython
Classifier: Intended Audience :: Developers
Classifier: Intended Audience :: Information Technology
Classifier: Intended Audience :: System Administrators
Classifier: License :: OSI Approved :: MIT License
Classifier: Operating System :: Unix
Classifier: Operating System :: POSIX :: Linux
Classifier: Operating System :: MacOS
Classifier: Operating System :: Microsoft
Classifier: Environment :: Console
Classifier: Topic :: Software Development :: Libraries :: Python Modules
Classifier: Topic :: Internet
Classifier: Topic :: Utilities
Classifier: Typing :: Typed
Classifier: Framework :: Pydantic
Classifier: Framework :: FastAPI
Classifier: Natural Language :: English
Requires-Dist: doppler-sdk (>=1.3.0,<2.0.0)
Requires-Dist: pydantic-settings (>=2.0,<3.0)
Project-URL: Bug Tracker, https://github.com/ajauniskis/pydantic-settings-doppler/issues
Project-URL: Changelog, https://github.com/ajauniskis/pydantic-settings-doppler/blob/main/CHANGELOG.md
Project-URL: Documentation, https://ajauniskis.github.io/pydantic-settings-doppler
Project-URL: Homepage, https://github.com/ajauniskis/pydantic-settings-doppler
Project-URL: Repository, https://github.com/ajauniskis/pydantic-settings-doppler
